VHDL_implementation/tpcn_cell.vhd
library ieee;
use ieee.std_logic_1164.all;
use ieee.numeric_std.all;

-- TPCN cell skeleton:
-- - 10 gated pathways
-- - local delayed error buffer
-- - fixed-point signed arithmetic (Q8.8)
entity tpcn_cell is
  generic (
    PATHWAYS       : positive := 10;
    DATA_WIDTH     : positive := 16;
    ERROR_BUF_SIZE : positive := 8
  );
  port (
    clk            : in  std_logic;
    rst            : in  std_logic;
    en             : in  std_logic;

    -- Current local state/input (Q8.8 signed)
    h_in           : in  signed(DATA_WIDTH - 1 downto 0);

    -- Flattened pathway outputs and gates: pathway k in slice [(k+1)*W-1 : k*W]
    pathway_vals   : in  signed(PATHWAYS * DATA_WIDTH - 1 downto 0);
    pathway_gates  : in  unsigned(PATHWAYS * DATA_WIDTH - 1 downto 0);

    -- Error signal (Q8.8 signed), optionally delayed by buffer
    err_in         : in  signed(DATA_WIDTH - 1 downto 0);
    use_delayed_err: in  std_logic;

    -- Tunables (Q8.8 unsigned)
    leak_alpha     : in  unsigned(DATA_WIDTH - 1 downto 0); -- blending for h memory
    err_gain       : in  unsigned(DATA_WIDTH - 1 downto 0); -- error correction gain

    h_out          : out signed(DATA_WIDTH - 1 downto 0);
    err_out        : out signed(DATA_WIDTH - 1 downto 0)
  );
end entity;

architecture rtl of tpcn_cell is
  subtype sfix_t is signed(DATA_WIDTH - 1 downto 0);
  subtype ufix_t is unsigned(DATA_WIDTH - 1 downto 0);

  type err_buf_t is array (0 to ERROR_BUF_SIZE - 1) of sfix_t;

  signal err_buf      : err_buf_t := (others => (others => '0'));
  signal err_wr_ptr   : integer range 0 to ERROR_BUF_SIZE - 1 := 0;
  signal err_rd_ptr   : integer range 0 to ERROR_BUF_SIZE - 1 := 0;

  signal h_reg        : sfix_t := (others => '0');
  signal mixed_reg    : sfix_t := (others => '0');
  signal selected_err : sfix_t := (others => '0');

  function sat_signed(v : integer; width : positive) return signed is
    variable vmax : integer := 2**(width - 1) - 1;
    variable vmin : integer := -2**(width - 1);
  begin
    if v > vmax then
      return to_signed(vmax, width);
    elsif v < vmin then
      return to_signed(vmin, width);
    else
      return to_signed(v, width);
    end if;
  end function;

begin
  process(clk)
    variable acc_mix      : integer;
    variable p_val_i      : integer;
    variable gate_i       : integer;
    variable mixed_i      : integer;
    variable leak_i       : integer;
    variable err_gain_i   : integer;
    variable h_i          : integer;
    variable err_i        : integer;
    variable next_h_i     : integer;
  begin
    if rising_edge(clk) then
      if rst = '1' then
        h_reg      <= (others => '0');
        mixed_reg  <= (others => '0');
        selected_err <= (others => '0');
        err_buf    <= (others => (others => '0'));
        err_wr_ptr <= 0;
        err_rd_ptr <= 0;
      elsif en = '1' then
        -- Delay line for local error
        err_buf(err_wr_ptr) <= err_in;
        if err_wr_ptr = ERROR_BUF_SIZE - 1 then
          err_wr_ptr <= 0;
        else
          err_wr_ptr <= err_wr_ptr + 1;
        end if;

        if err_rd_ptr = ERROR_BUF_SIZE - 1 then
          err_rd_ptr <= 0;
        else
          err_rd_ptr <= err_rd_ptr + 1;
        end if;

        if use_delayed_err = '1' then
          selected_err <= err_buf(err_rd_ptr);
        else
          selected_err <= err_in;
        end if;

        -- Gated pathway mix: sum_k((pathway_vals_k * pathway_gates_k) / 256)
        acc_mix := 0;
        for k in 0 to PATHWAYS - 1 loop
          p_val_i := to_integer(pathway_vals((k + 1) * DATA_WIDTH - 1 downto k * DATA_WIDTH));
          gate_i  := to_integer(pathway_gates((k + 1) * DATA_WIDTH - 1 downto k * DATA_WIDTH));
          acc_mix := acc_mix + ((p_val_i * gate_i) / 256);
        end loop;

        mixed_reg <= sat_signed(acc_mix, DATA_WIDTH);

        -- h_next = leak_alpha*h_prev + (1-leak_alpha)*mixed - err_gain*err
        h_i        := to_integer(h_reg);
        mixed_i    := to_integer(mixed_reg);
        leak_i     := to_integer(leak_alpha);
        err_gain_i := to_integer(err_gain);
        err_i      := to_integer(selected_err);

        next_h_i := ((leak_i * h_i) / 256)
                    + (((256 - leak_i) * mixed_i) / 256)
                    - ((err_gain_i * err_i) / 256);

        h_reg <= sat_signed(next_h_i, DATA_WIDTH);
      end if;
    end if;
  end process;

  h_out   <= h_reg;
  err_out <= selected_err;
end architecture;

VHDL_implementation/tb_tpcn_cell.vhd
library ieee;
use ieee.std_logic_1164.all;
use ieee.numeric_std.all;

entity tb_tpcn_cell is
end entity;

architecture sim of tb_tpcn_cell is
  constant PATHWAYS   : positive := 10;
  constant DATA_WIDTH : positive := 16;

  signal clk             : std_logic := '0';
  signal rst             : std_logic := '1';
  signal en              : std_logic := '0';
  signal h_in            : signed(DATA_WIDTH - 1 downto 0) := (others => '0');
  signal pathway_vals    : signed(PATHWAYS * DATA_WIDTH - 1 downto 0) := (others => '0');
  signal pathway_gates   : unsigned(PATHWAYS * DATA_WIDTH - 1 downto 0) := (others => '0');
  signal err_in          : signed(DATA_WIDTH - 1 downto 0) := (others => '0');
  signal use_delayed_err : std_logic := '0';
  signal leak_alpha      : unsigned(DATA_WIDTH - 1 downto 0) := to_unsigned(128, DATA_WIDTH); -- 0.5
  signal err_gain        : unsigned(DATA_WIDTH - 1 downto 0) := to_unsigned(32, DATA_WIDTH);  -- 0.125
  signal h_out           : signed(DATA_WIDTH - 1 downto 0);
  signal err_out         : signed(DATA_WIDTH - 1 downto 0);

  constant CLK_PERIOD : time := 10 ns;

  procedure set_pathway(
    signal vals  : inout signed(PATHWAYS * DATA_WIDTH - 1 downto 0);
    signal gates : inout unsigned(PATHWAYS * DATA_WIDTH - 1 downto 0);
    idx          : in integer;
    val_q88      : in integer;
    gate_q88     : in integer
  ) is
    variable lo : integer;
    variable hi : integer;
  begin
    lo := idx * DATA_WIDTH;
    hi := (idx + 1) * DATA_WIDTH - 1;
    vals(hi downto lo)  <= to_signed(val_q88, DATA_WIDTH);
    gates(hi downto lo) <= to_unsigned(gate_q88, DATA_WIDTH);
  end procedure;

begin
  clk <= not clk after CLK_PERIOD / 2;

  dut: entity work.tpcn_cell
    generic map (
      PATHWAYS       => PATHWAYS,
      DATA_WIDTH     => DATA_WIDTH,
      ERROR_BUF_SIZE => 8
    )
    port map (
      clk             => clk,
      rst             => rst,
      en              => en,
      h_in            => h_in,
      pathway_vals    => pathway_vals,
      pathway_gates   => pathway_gates,
      err_in          => err_in,
      use_delayed_err => use_delayed_err,
      leak_alpha      => leak_alpha,
      err_gain        => err_gain,
      h_out           => h_out,
      err_out         => err_out
    );

  stim: process
  begin
    -- Reset
    wait for 5 * CLK_PERIOD;
    rst <= '0';
    en  <= '1';

    -- Build pathway mix: two active pathways
    set_pathway(pathway_vals, pathway_gates, 0,  128, 256); -- +0.5 * 1.0
    set_pathway(pathway_vals, pathway_gates, 1, -64, 128);  -- -0.25 * 0.5

    -- Immediate error mode
    use_delayed_err <= '0';
    err_in <= to_signed(16, DATA_WIDTH); -- small positive error
    wait for 20 * CLK_PERIOD;

    -- Delayed error mode, change sign
    use_delayed_err <= '1';
    err_in <= to_signed(-24, DATA_WIDTH);
    wait for 20 * CLK_PERIOD;

    -- Increase error gain and observe stronger correction
    err_gain <= to_unsigned(64, DATA_WIDTH); -- 0.25
    wait for 20 * CLK_PERIOD;

    report "TB completed" severity note;
    wait;
  end process;

  checker: process(clk)
  begin
    if rising_edge(clk) then
      if rst = '0' and en = '1' then
        assert h_out'length = DATA_WIDTH
          report "Unexpected h_out width"
          severity error;
      end if;
    end if;
  end process;
end architecture;

VHDL_implementation/tpcn_cell_tb.vcd
$date
  Tue Mar 31 15:38:47 2026
$end
$version
  GHDL v0
$end
$timescale
  1 fs
$end
$scope module standard $end
$upscope $end
$scope module textio $end
$upscope $end
$scope module std_logic_1164 $end
$upscope $end
$scope module numeric_std $end
$upscope $end
$scope module tb_tpcn_cell $end
$var reg 1 ! clk $end
$var reg 1 " rst $end
$var reg 1 # en $end
$var reg 16 $ h_in[15:0] $end
$var reg 160 % pathway_vals[159:0] $end
$var reg 160 & pathway_gates[159:0] $end
$var reg 16 ' err_in[15:0] $end
$var reg 1 ( use_delayed_err $end
$var reg 16 ) leak_alpha[15:0] $end
$var reg 16 * err_gain[15:0] $end
$var reg 16 + h_out[15:0] $end
$var reg 16 , err_out[15:0] $end
$scope module dut $end
$var reg 1 - clk $end
$var reg 1 . rst $end
$var reg 1 / en $end
$var reg 16 0 h_in[15:0] $end
$var reg 160 1 pathway_vals[159:0] $end
$var reg 160 2 pathway_gates[159:0] $end
$var reg 16 3 err_in[15:0] $end
$var reg 1 4 use_delayed_err $end
$var reg 16 5 leak_alpha[15:0] $end
$var reg 16 6 err_gain[15:0] $end
$var reg 16 7 h_out[15:0] $end
$var reg 16 8 err_out[15:0] $end
$comment err_buf is not handled $end
$var integer 32 9 err_wr_ptr $end
$var integer 32 : err_rd_ptr $end
$var reg 16 ; h_reg[15:0] $end
$var reg 16 < mixed_reg[15:0] $end
$var reg 16 = selected_err[15:0] $end
$upscope $end
$upscope $end
$enddefinitions $end
#0
0!
1"
0#
b0000000000000000 $
b0000000000000000000000000000000000000000000000000000000000000000000000000000000000000000000000000000000000000000000000000000000000000000000000000000000000000000 %
b0000000000000000000000000000000000000000000000000000000000000000000000000000000000000000000000000000000000000000000000000000000000000000000000000000000000000000 &
b0000000000000000 '
0(
b0000000010000000 )
b0000000000100000 *
b0000000000000000 +
b0000000000000000 ,
0-
1.
0/
b0000000000000000 0
b0000000000000000000000000000000000000000000000000000000000000000000000000000000000000000000000000000000000000000000000000000000000000000000000000000000000000000 1
b0000000000000000000000000000000000000000000000000000000000000000000000000000000000000000000000000000000000000000000000000000000000000000000000000000000000000000 2
b0000000000000000 3
04
b0000000010000000 5
b0000000000100000 6
b0000000000000000 7
b0000000000000000 8
b0 9
b0 :
b0000000000000000 ;
b0000000000000000 <
b0000000000000000 =
#5000000
1!
1-
#10000000
0!
0-
#15000000
1!
1-
#20000000
0!
0-
#25000000
1!
1-
#30000000
0!
0-
#35000000
1!
1-
#40000000
0!
0-
#45000000
1!
1-
#50000000
0!
0"
1#
b0000000000000000000000000000000000000000000000000000000000000000000000000000000000000000000000000000000000000000000000000000000011111111110000000000000010000000 %
b0000000000000000000000000000000000000000000000000000000000000000000000000000000000000000000000000000000000000000000000000000000000000000100000000000000100000000 &
b0000000000010000 '
0-
0.
1/
b0000000000000000000000000000000000000000000000000000000000000000000000000000000000000000000000000000000000000000000000000000000011111111110000000000000010000000 1
b0000000000000000000000000000000000000000000000000000000000000000000000000000000000000000000000000000000000000000000000000000000000000000100000000000000100000000 2
b0000000000010000 3
#55000000
1!
b0000000000010000 ,
1-
b0000000000010000 8
b1 9
b1 :
b0000000001100000 <
b0000000000010000 =
#60000000
0!
0-
#65000000
1!
b0000000000101110 +
1-
b0000000000101110 7
b10 9
b10 :
b0000000000101110 ;
#70000000
0!
0-
#75000000
1!
b0000000001000101 +
1-
b0000000001000101 7
b11 9
b11 :
b0000000001000101 ;
#80000000
0!
0-
#85000000
1!
b0000000001010000 +
1-
b0000000001010000 7
b100 9
b100 :
b0000000001010000 ;
#90000000
0!
0-
#95000000
1!
b0000000001010110 +
1-
b0000000001010110 7
b101 9
b101 :
b0000000001010110 ;
#100000000
0!
0-
#105000000
1!
b0000000001011001 +
1-
b0000000001011001 7
b110 9
b110 :
b0000000001011001 ;
#110000000
0!
0-
#115000000
1!
b0000000001011010 +
1-
b0000000001011010 7
b111 9
b111 :
b0000000001011010 ;
#120000000
0!
0-
#125000000
1!
b0000000001011011 +
1-
b0000000001011011 7
b0 9
b0 :
b0000000001011011 ;
#130000000
0!
0-
#135000000
1!
1-
b1 9
b1 :
#140000000
0!
0-
#145000000
1!
1-
b10 9
b10 :
#150000000
0!
0-
#155000000
1!
1-
b11 9
b11 :
#160000000
0!
0-
#165000000
1!
1-
b100 9
b100 :
#170000000
0!
0-
#175000000
1!
1-
b101 9
b101 :
#180000000
0!
0-
#185000000
1!
1-
b110 9
b110 :
#190000000
0!
0-
#195000000
1!
1-
b111 9
b111 :
#200000000
0!
0-
#205000000
1!
1-
b0 9
b0 :
#210000000
0!
0-
#215000000
1!
1-
b1 9
b1 :
#220000000
0!
0-
#225000000
1!
1-
b10 9
b10 :
#230000000
0!
0-
#235000000
1!
1-
b11 9
b11 :
#240000000
0!
0-
#245000000
1!
1-
b100 9
b100 :
#250000000
0!
b1111111111101000 '
1(
0-
b1111111111101000 3
14
#255000000
1!
1-
b101 9
b101 :
#260000000
0!
0-
#265000000
1!
1-
b110 9
b110 :
#270000000
0!
0-
#275000000
1!
1-
b111 9
b111 :
#280000000
0!
0-
#285000000
1!
1-
b0 9
b0 :
#290000000
0!
0-
#295000000
1!
1-
b1 9
b1 :
#300000000
0!
0-
#305000000
1!
1-
b10 9
b10 :
#310000000
0!
0-
#315000000
1!
1-
b11 9
b11 :
#320000000
0!
0-
#325000000
1!
1-
b100 9
b100 :
#330000000
0!
0-
#335000000
1!
b1111111111101000 ,
1-
b1111111111101000 8
b101 9
b101 :
b1111111111101000 =
#340000000
0!
0-
#345000000
1!
b0000000001100000 +
1-
b0000000001100000 7
b110 9
b110 :
b0000000001100000 ;
#350000000
0!
0-
#355000000
1!
b0000000001100011 +
1-
b0000000001100011 7
b111 9
b111 :
b0000000001100011 ;
#360000000
0!
0-
#365000000
1!
b0000000001100100 +
1-
b0000000001100100 7
b0 9
b0 :
b0000000001100100 ;
#370000000
0!
0-
#375000000
1!
b0000000001100101 +
1-
b0000000001100101 7
b1 9
b1 :
b0000000001100101 ;
#380000000
0!
0-
#385000000
1!
1-
b10 9
b10 :
#390000000
0!
0-
#395000000
1!
1-
b11 9
b11 :
#400000000
0!
0-
#405000000
1!
1-
b100 9
b100 :
#410000000
0!
0-
#415000000
1!
1-
b101 9
b101 :
#420000000
0!
0-
#425000000
1!
1-
b110 9
b110 :
#430000000
0!
0-
#435000000
1!
1-
b111 9
b111 :
#440000000
0!
0-
#445000000
1!
1-
b0 9
b0 :
#450000000
0!
b0000000001000000 *
0-
b0000000001000000 6
#455000000
1!
b0000000001101000 +
1-
b0000000001101000 7
b1 9
b1 :
b0000000001101000 ;
#460000000
0!
0-
#465000000
1!
b0000000001101010 +
1-
b0000000001101010 7
b10 9
b10 :
b0000000001101010 ;
#470000000
0!
0-
#475000000
1!
b0000000001101011 +
1-
b0000000001101011 7
b11 9
b11 :
b0000000001101011 ;
#480000000
0!
0-
#485000000
1!
1-
b100 9
b100 :
#490000000
0!
0-
#495000000
1!
1-
b101 9
b101 :
#500000000
0!
0-
#505000000
1!
1-
b110 9
b110 :
#510000000
0!
0-
#515000000
1!
1-
b111 9
b111 :
#520000000
0!
0-
#525000000
1!
1-
b0 9
b0 :
#530000000
0!
0-
#535000000
1!
1-
b1 9
b1 :
#540000000
0!
0-
#545000000
1!
1-
b10 9
b10 :
#550000000
0!
0-
#555000000
1!
1-
b11 9
b11 :
#560000000
0!
0-
#565000000
1!
1-
b100 9
b100 :
#570000000
0!
0-
#575000000
1!
1-
b101 9
b101 :
#580000000
0!
0-
#585000000
1!
1-
b110 9
b110 :
#590000000
0!
0-
#595000000
1!
1-
b111 9
b111 :
#600000000
0!
0-
#605000000
1!
1-
b0 9
b0 :
#610000000
0!
0-
#615000000
1!
1-
b1 9
b1 :
#620000000
0!
0-
#625000000
1!
1-
b10 9
b10 :
#630000000
0!
0-
#635000000
1!
1-
b11 9
b11 :
#640000000
0!
0-
#645000000
1!
1-
b100 9
b100 :
#650000000
0!
0-
#655000000
1!
1-
b101 9
b101 :
#660000000
0!
0-
#665000000
1!
1-
b110 9
b110 :
#670000000
0!
0-
#675000000
1!
1-
b111 9
b111 :
#680000000
0!
0-
#685000000
1!
1-
b0 9
b0 :
#690000000
0!
0-
#695000000
1!
1-
b1 9
b1 :
#700000000
0!
0-
#705000000
1!
1-
b10 9
b10 :
#710000000
0!
0-
#715000000
1!
1-
b11 9
b11 :
#720000000
0!
0-
#725000000
1!
1-
b100 9
b100 :
#730000000
0!
0-
#735000000
1!
1-
b101 9
b101 :
#740000000
0!
0-
#745000000
1!
1-
b110 9
b110 :
#750000000
0!
0-
#755000000
1!
1-
b111 9
b111 :
#760000000
0!
0-
#765000000
1!
1-
b0 9
b0 :
#770000000
0!
0-
#775000000
1!
1-
b1 9
b1 :
#780000000
0!
0-
#785000000
1!
1-
b10 9
b10 :
#790000000
0!
0-
#795000000
1!
1-
b11 9
b11 :
#800000000
0!
0-
#805000000
1!
1-
b100 9
b100 :
#810000000
0!
0-
#815000000
1!
1-
b101 9
b101 :
#820000000
0!
0-
#825000000
1!
1-
b110 9
b110 :
#830000000
0!
0-
#835000000
1!
1-
b111 9
b111 :
#840000000
0!
0-
#845000000
1!
1-
b0 9
b0 :
#850000000
0!
0-
#855000000
1!
1-
b1 9
b1 :
#860000000
0!
0-
#865000000
1!
1-
b10 9
b10 :
#870000000
0!
0-
#875000000
1!
1-
b11 9
b11 :
#880000000
0!
0-
#885000000
1!
1-
b100 9
b100 :
#890000000
0!
0-
#895000000
1!
1-
b101 9
b101 :
#900000000
0!
0-
#905000000
1!
1-
b110 9
b110 :
#910000000
0!
0-
#915000000
1!
1-
b111 9
b111 :
#920000000
0!
0-
#925000000
1!
1-
b0 9
b0 :
#930000000
0!
0-
#935000000
1!
1-
b1 9
b1 :
#940000000
0!
0-
#945000000
1!
1-
b10 9
b10 :
#950000000
0!
0-
#955000000
1!
1-
b11 9
b11 :
#960000000
0!
0-
#965000000
1!
1-
b100 9
b100 :
#970000000
0!
0-
#975000000
1!
1-
b101 9
b101 :
#980000000
0!
0-
#985000000
1!
1-
b110 9
b110 :
#990000000
0!
0-
#995000000
1!
1-
b111 9
b111 :
